sol_add/__init__.py
sol_add/add.py
sol_add-0.1.0.dist-info/METADATA
sol_add-0.1.0.dist-info/WHEEL
sol_add-0.1.0.dist-info/top_level.txt
sol_add-0.1.0.dist-info/RECORD
